Metadata-Version: 2.1
Name: pycha
Version: 0.8.0
Summary: A library for making charts with Python
Home-page: http://bitbucket.org/lgs/pycha/
Author: Lorenzo Gil Sanchez
Author-email: lorenzo.gil.sanchez@gmail.com
License: LGPL 3
Keywords: chart cairo
Platform: UNKNOWN
Provides-Extra: testing
